README.rst
setup.cfg
setup.py
appinsights.egg-info/PKG-INFO
appinsights.egg-info/SOURCES.txt
appinsights.egg-info/dependency_links.txt
appinsights.egg-info/requires.txt
appinsights.egg-info/top_level.txt
applicationinsights/TelemetryClient.py
applicationinsights/__init__.py
applicationinsights/bottle/__init__.py
applicationinsights/bottle/plugin.py
applicationinsights/channel/AsynchronousQueue.py
applicationinsights/channel/AsynchronousSender.py
applicationinsights/channel/NullSender.py
applicationinsights/channel/QueueBase.py
applicationinsights/channel/SenderBase.py
applicationinsights/channel/SynchronousQueue.py
applicationinsights/channel/SynchronousSender.py
applicationinsights/channel/TelemetryChannel.py
applicationinsights/channel/TelemetryContext.py
applicationinsights/channel/__init__.py
applicationinsights/channel/contracts/Application.py
applicationinsights/channel/contracts/AvailabilityData.py
applicationinsights/channel/contracts/Base.py
applicationinsights/channel/contracts/Cloud.py
applicationinsights/channel/contracts/Data.py
applicationinsights/channel/contracts/DataPoint.py
applicationinsights/channel/contracts/DataPointType.py
applicationinsights/channel/contracts/Device.py
applicationinsights/channel/contracts/Domain.py
applicationinsights/channel/contracts/Envelope.py
applicationinsights/channel/contracts/EventData.py
applicationinsights/channel/contracts/ExceptionData.py
applicationinsights/channel/contracts/ExceptionDetails.py
applicationinsights/channel/contracts/Internal.py
applicationinsights/channel/contracts/Location.py
applicationinsights/channel/contracts/MessageData.py
applicationinsights/channel/contracts/MetricData.py
applicationinsights/channel/contracts/Operation.py
applicationinsights/channel/contracts/PageViewData.py
applicationinsights/channel/contracts/PageViewPerfData.py
applicationinsights/channel/contracts/RemoteDependencyData.py
applicationinsights/channel/contracts/RequestData.py
applicationinsights/channel/contracts/Session.py
applicationinsights/channel/contracts/SeverityLevel.py
applicationinsights/channel/contracts/StackFrame.py
applicationinsights/channel/contracts/User.py
