Metadata-Version: 2.1
Name: appinsights
Version: 0.13.0
Summary: This project extends the Application Insights API surface to support Python.
Home-page: https://github.com/brennerm/python-appinsights
Author: Max Brenner
Author-email: xamrennerb@gmail.com
License: MIT
Download-URL: https://github.com/brennerm/python-appinsights
Keywords: analytics applicationinsights telemetry appinsights development
Platform: UNKNOWN
Classifier: Development Status :: 3 - Alpha
Classifier: Intended Audience :: Developers
Classifier: Topic :: Software Development :: Libraries :: Python Modules
Classifier: Operating System :: OS Independent
Classifier: License :: OSI Approved :: MIT License
Classifier: Programming Language :: Python :: 2.7
Classifier: Programming Language :: Python :: 3.4
Classifier: Programming Language :: Python :: 3.5
Classifier: Programming Language :: Python :: 3.6
Provides-Extra: requests-client
Provides-Extra: urllib3-client
